bgpy/__init__.py
bgpy/cli.py
bgpy/client.py
bgpy/core/__init__.py
bgpy/core/environment.py
bgpy/core/log.py
bgpy/core/message.py
bgpy/core/serialize.py
bgpy/core/sockets.py
bgpy/core/token.py
bgpy/example/__init__.py
bgpy/example/tasks.py
bgpy/server.py
bgpy-0.3.1.dist-info/entry_points.txt
bgpy-0.3.1.dist-info/LICENSE
bgpy-0.3.1.dist-info/WHEEL
bgpy-0.3.1.dist-info/METADATA
bgpy-0.3.1.dist-info/RECORD
