Metadata-Version: 2.1
Name: bgpy
Version: 0.3.1
Summary: Running local or remote Python servers in the background and establish stream socket-based communication with clients.
Home-page: https://pypi.org/project/bgpy/
License: MIT
Author: Merlin Unterfinger
Author-email: info@munterfinger.ch
Maintainer: Merlin Unterfinger
Maintainer-email: info@munterfinger.ch
Requires-Python: >=3.6,<4.0
Classifier: License :: OSI Approved :: MIT License
Classifier: Programming Language :: Python :: 3
Classifier: Programming Language :: Python :: 3.6
Classifier: Programming Language :: Python :: 3.7
Classifier: Programming Language :: Python :: 3.8
Classifier: Programming Language :: Python :: 3.9
Requires-Dist: importlib-metadata (>=3.4,<5.0); python_version < "3.8"
Requires-Dist: typer (>=0.3.2,<0.5.0)
Project-URL: Documentation, https://bgpy.readthedocs.io/en/latest/
Project-URL: Repository, https://github.com/munterfi/bgpy
